pyvgmdb/__init__.py
pyvgmdb/album.py
pyvgmdb/artist.py
pyvgmdb/automatic.py
pyvgmdb/notes.py
pyvgmdb/re_tools.py
pyvgmdb/thread_tools.py
pyvgmdb/utils.py
pyvgmdb/xpaths.py
pyvgmdb-0.1.5.dist-info/LICENSE
pyvgmdb-0.1.5.dist-info/METADATA
pyvgmdb-0.1.5.dist-info/WHEEL
pyvgmdb-0.1.5.dist-info/top_level.txt
pyvgmdb-0.1.5.dist-info/RECORD
